[
    {
        "date": "2019-12-31",
        "symbol": "CSGP",
        "reportedCurrency": "USD",
        "fillingDate": "2020-02-26 00:00:00",
        "acceptedDate": "2020-02-26 16:15:47",
        "period": "FY",
        "netIncome": 314963000,
        "depreciationAndAmortization": 81165000,
        "deferredIncomeTax": 8220000,
        "stockBasedCompensation": 52255000,
        "changeInWorkingCapital": -86951000,
        "accountsReceivables": -5014000,
        "inventory": 0,
        "accountsPayables": 17751000,
        "otherWorkingCapital": -59425000,
        "otherNonCashItems": 77045000,
        "netCashProvidedByOperatingActivities": 457780000,
        "investmentsInPropertyPlantAndEquipment": 0,
        "acquisitionsNet": 0,
        "purchasesOfInvestments": 0,
        "salesMaturitiesOfInvestments": 0,
        "otherInvestingActivites": 0,
        "netCashUsedForInvestingActivites": 0,
        "debtRepayment": 0,
        "commonStockIssued": 0,
        "commonStockRepurchased": -27577000,
        "dividendsPaid": 0,
        "otherFinancingActivites": -1657000,
        "netCashUsedProvidedByFinancingActivities": 0,
        "effectOfForexChangesOnCash": 0,
        "netChangeInCash": 0,
        "cashAtEndOfPeriod": 1070731000,
        "cashAtBeginningOfPeriod": 1100416000,
        "operatingCashFlow": 457780000,
        "capitalExpenditure": -46197000,
        "freeCashFlow": 411583000,
        "link": "https://www.sec.gov/Archives/edgar/data/1057352/000105735220000036/0001057352-20-000036-index.html",
        "finalLink": "https://www.sec.gov/Archives/edgar/data/1057352/000105735220000036/csgp20191231-10k.htm"
    },
    {
        "date": "2018-12-31",
        "symbol": "CSGP",
        "reportedCurrency": "USD",
        "fillingDate": "2019-02-28 00:00:00",
        "acceptedDate": "2019-02-28 14:04:18",
        "period": "FY",
        "netIncome": 238334000,
        "depreciationAndAmortization": 77743000,
        "deferredIncomeTax": 3666000,
        "stockBasedCompensation": 41214000,
        "changeInWorkingCapital": -81303000,
        "accountsReceivables": -27819000,
        "inventory": 0,
        "accountsPayables": -14132000,
        "otherWorkingCapital": -45406000,
        "otherNonCashItems": 49189000,
        "netCashProvidedByOperatingActivities": 335458000,
        "investmentsInPropertyPlantAndEquipment": 0,
        "acquisitionsNet": 0,
        "purchasesOfInvestments": 0,
        "salesMaturitiesOfInvestments": 0,
        "otherInvestingActivites": 0,
        "netCashUsedForInvestingActivites": 0,
        "debtRepayment": 0,
        "commonStockIssued": 0,
        "commonStockRepurchased": -24327000,
        "dividendsPaid": 0,
        "otherFinancingActivites": 0,
        "netCashUsedProvidedByFinancingActivities": 0,
        "effectOfForexChangesOnCash": 0,
        "netChangeInCash": 0,
        "cashAtEndOfPeriod": 1100416000,
        "cashAtBeginningOfPeriod": 1211463000,
        "operatingCashFlow": 335458000,
        "capitalExpenditure": -29632000,
        "freeCashFlow": 305826000,
        "link": "https://www.sec.gov/Archives/edgar/data/1057352/000105735219000017/0001057352-19-000017-index.html",
        "finalLink": "https://www.sec.gov/Archives/edgar/data/1057352/000105735219000017/csgp20181231-10k.htm"
    },
    {
        "date": "2017-12-31",
        "symbol": "CSGP",
        "reportedCurrency": "USD",
        "fillingDate": "2018-02-23 00:00:00",
        "acceptedDate": "2018-02-22 19:09:26",
        "period": "FY",
        "netIncome": 122695000,
        "depreciationAndAmortization": 63643000,
        "deferredIncomeTax": -2903000,
        "stockBasedCompensation": 39030000,
        "changeInWorkingCapital": 328000,
        "accountsReceivables": -17524000,
        "inventory": 0,
        "accountsPayables": 11525000,
        "otherWorkingCapital": 6043000,
        "otherNonCashItems": 2303000,
        "netCashProvidedByOperatingActivities": 234703000,
        "investmentsInPropertyPlantAndEquipment": 0,
        "acquisitionsNet": 0,
        "purchasesOfInvestments": 0,
        "salesMaturitiesOfInvestments": 0,
        "otherInvestingActivites": 0,
        "netCashUsedForInvestingActivites": 0,
        "debtRepayment": -345000000,
        "commonStockIssued": 833911000,
        "commonStockRepurchased": -14902000,
        "dividendsPaid": 0,
        "otherFinancingActivites": -3467000,
        "netCashUsedProvidedByFinancingActivities": 0,
        "effectOfForexChangesOnCash": 0,
        "netChangeInCash": 0,
        "cashAtEndOfPeriod": 1211463000,
        "cashAtBeginningOfPeriod": 567223000,
        "operatingCashFlow": 234703000,
        "capitalExpenditure": -24499000,
        "freeCashFlow": 210204000,
        "link": "https://www.sec.gov/Archives/edgar/data/1057352/000105735218000011/0001057352-18-000011-index.html",
        "finalLink": "https://www.sec.gov/Archives/edgar/data/1057352/000105735218000011/csgp20171231-10k.htm"
    },
    {
        "date": "2016-12-31",
        "symbol": "CSGP",
        "reportedCurrency": "USD",
        "fillingDate": "2017-02-24 00:00:00",
        "acceptedDate": "2017-02-23 18:21:15",
        "period": "FY",
        "netIncome": 85071000,
        "depreciationAndAmortization": 70165000,
        "deferredIncomeTax": 15635000,
        "stockBasedCompensation": 36349000,
        "changeInWorkingCapital": -17217000,
        "accountsReceivables": -16044000,
        "inventory": 0,
        "accountsPayables": -1520000,
        "otherWorkingCapital": -1312000,
        "otherNonCashItems": 3227000,
        "netCashProvidedByOperatingActivities": 195944000,
        "investmentsInPropertyPlantAndEquipment": 0,
        "acquisitionsNet": 0,
        "purchasesOfInvestments": 0,
        "salesMaturitiesOfInvestments": 5950000,
        "otherInvestingActivites": 0,
        "netCashUsedForInvestingActivites": 0,
        "debtRepayment": -20000000,
        "commonStockIssued": 0,
        "commonStockRepurchased": -16424000,
        "dividendsPaid": 0,
        "otherFinancingActivites": 4698000,
        "netCashUsedProvidedByFinancingActivities": 0,
        "effectOfForexChangesOnCash": 0,
        "netChangeInCash": 0,
        "cashAtEndOfPeriod": 567223000,
        "cashAtBeginningOfPeriod": 421818000,
        "operatingCashFlow": 195944000,
        "capitalExpenditure": -18766000,
        "freeCashFlow": 177178000,
        "link": "https://www.sec.gov/Archives/edgar/data/1057352/000105735217000008/0001057352-17-000008-index.html",
        "finalLink": "https://www.sec.gov/Archives/edgar/data/1057352/000105735217000008/csgp20161231-10k.htm"
    },
    {
        "date": "2015-12-31",
        "symbol": "CSGP",
        "reportedCurrency": "USD",
        "fillingDate": "2016-02-26 00:00:00",
        "acceptedDate": "2016-02-25 18:57:53",
        "period": "FY",
        "netIncome": -3465000,
        "depreciationAndAmortization": 78532000,
        "deferredIncomeTax": -5792000,
        "stockBasedCompensation": 34537000,
        "changeInWorkingCapital": 22189000,
        "accountsReceivables": -3999000,
        "inventory": 0,
        "accountsPayables": 9938000,
        "otherWorkingCapital": 4503000,
        "otherNonCashItems": 3311000,
        "netCashProvidedByOperatingActivities": 131245000,
        "investmentsInPropertyPlantAndEquipment": 0,
        "acquisitionsNet": 0,
        "purchasesOfInvestments": 0,
        "salesMaturitiesOfInvestments": 1900000,
        "otherInvestingActivites": 0,
        "netCashUsedForInvestingActivites": 0,
        "debtRepayment": -20000000,
        "commonStockIssued": 0,
        "commonStockRepurchased": -16436000,
        "dividendsPaid": 0,
        "otherFinancingActivites": 8528000,
        "netCashUsedProvidedByFinancingActivities": 0,
        "effectOfForexChangesOnCash": 0,
        "netChangeInCash": 0,
        "cashAtEndOfPeriod": 421818000,
        "cashAtBeginningOfPeriod": 527012000,
        "operatingCashFlow": 131245000,
        "capitalExpenditure": -35061000,
        "freeCashFlow": 96184000,
        "link": "https://www.sec.gov/Archives/edgar/data/1057352/000105735216000103/0001057352-16-000103-index.html",
        "finalLink": "https://www.sec.gov/Archives/edgar/data/1057352/000105735216000103/csgp20151231-10k.htm"
    }
]