[
    {
        "symbol": "MRK",
        "date": "2019-12-31",
        "revenuePerShare": 18.448091512755187,
        "netIncomePerShare": 3.8766986498729565,
        "operatingCashFlowPerShare": 5.293389195803367,
        "freeCashFlowPerShare": 3.9255364668580475,
        "cashPerShare": 3.8109251382881975,
        "bookValuePerShare": 10.203559069618885,
        "tangibleBookValuePerShare": 19.998298348669028,
        "shareholdersEquityPerShare": 10.203559069618885,
        "interestDebtPerShare": 9.61120361199327,
        "marketCap": 216107587348.1822,
        "enterpriseValue": 229941587348.1822,
        "peRatio": 21.955459448154244,
        "priceToSalesRatio": 4.613740122719517,
        "pocfratio": 16.079433582454033,
        "pfcfRatio": 21.68231035900293,
        "pbRatio": 8.34166778662841,
        "ptbRatio": 8.34166778662841,
        "evToSales": 4.909085980960337,
        "enterpriseValueOverEBITDA": 13.798703033376272,
        "evToOperatingCashFlow": 17.10874905864451,
        "evToFreeCashFlow": 23.070290694108778,
        "earningsYield": 0.04554675807907396,
        "freeCashFlowYield": 0.046120546355189494,
        "debtToEquity": 2.2540626085613926,
        "debtToAssets": 0.6919203289216441,
        "netDebtToEBITDA": 0.8301728276524244,
        "currentRatio": 1.2368586858685868,
        "interestCoverage": 12.837625979843224,
        "incomeQuality": 1.3654373666565072,
        "dividendYield": 0.026352614778047977,
        "payoutRatio": 0.5785837651122625,
        "salesGeneralAndAdministrativeToRevenue": 0.0,
        "researchAndDdevelopementToRevenue": 0.2107600341588386,
        "intangiblesToTotalAssets": 0.3983672405417254,
        "capexToOperatingCashFlow": -3.869853152893752,
        "capexToRevenue": -13.48689893463864,
        "capexToDepreciation": -1.0515404549380938,
        "stockBasedCompensationToRevenue": 0.008902647309991461,
        "grahamNumber": 29.833082015684134,
        "roic": 0.1843768596104669,
        "returnOnTangibleAssets": 0.19385142587049,
        "grahamNetNet": -15.704312060927496,
        "workingCapital": 5263000000,
        "tangibleAssetValue": -7620000000,
        "netCurrentAssetValue": -30913000000,
        "investedCapital": null,
        "averageReceivables": 6924500000,
        "averagePayables": 3528000000,
        "averageInventory": 5709000000,
        "daysSalesOutstanding": 52.81746370623399,
        "daysPayablesOutstanding": 96.68154761904762,
        "daysOfInventoryOnHand": 154.61805555555554,
        "receivablesTurnover": 6.910593095308351,
        "payablesTurnover": 3.7752808988764044,
        "inventoryTurnover": 2.360655737704918,
        "roe": 0.3799359246535685,
        "capexPerShare": -1.3678527289453193
    },
    {
        "symbol": "MRK",
        "date": "2018-12-31",
        "revenuePerShare": 16.313607960980203,
        "netIncomePerShare": 2.3991734410861323,
        "operatingCashFlowPerShare": 4.212825132402369,
        "freeCashFlowPerShare": 3.204169417219051,
        "cashPerShare": 3.0722534498795886,
        "bookValuePerShare": 10.299088432546755,
        "tangibleBookValuePerShare": 20.42498894306012,
        "shareholdersEquityPerShare": 10.299088432546755,
        "interestDebtPerShare": 8.284091317396602,
        "marketCap": 182206121705.8572,
        "enterpriseValue": 194946121705.8572,
        "peRatio": 29.293588698690865,
        "priceToSalesRatio": 4.308084402181331,
        "pocfratio": 16.68248688022864,
        "pfcfRatio": 21.934046190665367,
        "pbRatio": 6.823943736409018,
        "ptbRatio": 6.823943736409018,
        "evToSales": 4.609309162194571,
        "enterpriseValueOverEBITDA": 13.495750896909463,
        "evToOperatingCashFlow": 17.84893991080912,
        "evToFreeCashFlow": 23.467692513044085,
        "earningsYield": 0.03413716258140438,
        "freeCashFlowYield": 0.045591223402528316,
        "debtToEquity": 2.088124040298116,
        "debtToAssets": 0.674697774604596,
        "netDebtToEBITDA": 0.8819660782277605,
        "currentRatio": 1.16522561469873,
        "interestCoverage": 11.270725388601036,
        "incomeQuality": 1.7559485530546624,
        "dividendYield": 0.028385434866724023,
        "payoutRatio": 0.8315112540192926,
        "salesGeneralAndAdministrativeToRevenue": 0.0,
        "researchAndDdevelopementToRevenue": 0.23057644110275688,
        "intangiblesToTotalAssets": 0.35920955504193036,
        "capexToOperatingCashFlow": -4.176673040152964,
        "capexToRevenue": -16.1736137667304,
        "capexToDepreciation": -1.7281070745697897,
        "stockBasedCompensationToRevenue": 0.008228117463469995,
        "grahamNumber": 23.578787867110144,
        "roic": 0.14398239314259237,
        "returnOnTangibleAssets": 0.11746265556247994,
        "grahamNetNet": -14.99203754256841,
        "workingCapital": 3669000000,
        "tangibleAssetValue": -2802000000,
        "netCurrentAssetValue": -29880000000,
        "investedCapital": null,
        "averageReceivables": 7071000000,
        "averagePayables": 3318000000,
        "averageInventory": 5440000000,
        "daysSalesOutstanding": 61.02319477940134,
        "daysPayablesOutstanding": 89.64912280701755,
        "daysOfInventoryOnHand": 146.9834924864905,
        "receivablesTurnover": 5.981332201951633,
        "payablesTurnover": 4.071428571428571,
        "inventoryTurnover": 2.4832720588235295,
        "roe": 0.2329500767761507,
        "capexPerShare": -1.0086557151833175
    },
    {
        "symbol": "MRK",
        "date": "2017-12-31",
        "revenuePerShare": 14.87867213838679,
        "netIncomePerShare": 0.8877807960544832,
        "operatingCashFlowPerShare": 2.390778108673038,
        "freeCashFlowPerShare": 1.690640204349369,
        "cashPerShare": 2.2591314158579414,
        "bookValuePerShare": 12.733016463377918,
        "tangibleBookValuePerShare": 20.546154973015305,
        "shareholdersEquityPerShare": 12.733016463377918,
        "interestDebtPerShare": 9.09029684782103,
        "marketCap": 152003412103.22638,
        "enterpriseValue": 169670412103.22638,
        "peRatio": 63.493488764923306,
        "priceToSalesRatio": 3.788530285210767,
        "pocfratio": 23.57738670749595,
        "pfcfRatio": 33.34139331064409,
        "pbRatio": 4.426940007666192,
        "ptbRatio": 4.426940007666192,
        "evToSales": 4.22886227264908,
        "enterpriseValueOverEBITDA": 13.384113915218615,
        "evToOperatingCashFlow": 26.317731053703486,
        "evToFreeCashFlow": 37.216585238698485,
        "earningsYield": 0.015749646451187694,
        "freeCashFlowYield": 0.029992747774003632,
        "debtToEquity": 1.5523939888164027,
        "debtToAssets": 0.6065982337946103,
        "netDebtToEBITDA": 1.3936262522678868,
        "currentRatio": 1.330503921779306,
        "interestCoverage": 8.648541114058355,
        "incomeQuality": 2.692982456140351,
        "dividendYield": 0.033992657983829076,
        "payoutRatio": 2.158312447786132,
        "salesGeneralAndAdministrativeToRevenue": 0.2450027416380041,
        "researchAndDdevelopementToRevenue": 0.2544240067793231,
        "intangiblesToTotalAssets": 0.36948060815731976,
        "capexToOperatingCashFlow": -3.4147245762711864,
        "capexToRevenue": -21.2510593220339,
        "capexToDepreciation": -2.45603813559322,
        "stockBasedCompensationToRevenue": 0.007776282338866457,
        "grahamNumber": 15.948130566644197,
        "roic": 0.09415518784833521,
        "returnOnTangibleAssets": 0.04320909665192672,
        "grahamNetNet": -13.758840869011047,
        "workingCapital": 6152000000,
        "tangibleAssetValue": 2102000000,
        "netCurrentAssetValue": -28537000000,
        "investedCapital": null,
        "averageReceivables": 6972000000,
        "averagePayables": 3210000000,
        "averageInventory": 5268000000,
        "daysSalesOutstanding": 62.52542246149245,
        "daysPayablesOutstanding": 88.62857142857143,
        "daysOfInventoryOnHand": 145.6,
        "receivablesTurnover": 5.837625491051942,
        "payablesTurnover": 4.118310767246937,
        "inventoryTurnover": 2.506868131868132,
        "roe": 0.06972273998136067,
        "capexPerShare": -0.7001379043236693
    },
    {
        "symbol": "MRK",
        "date": "2016-12-31",
        "revenuePerShare": 14.481953794973345,
        "netIncomePerShare": 1.426112464548836,
        "operatingCashFlowPerShare": 3.774832380652735,
        "freeCashFlowPerShare": 3.1876524016267602,
        "cashPerShare": 2.3701843639121596,
        "bookValuePerShare": 14.584182775212687,
        "tangibleBookValuePerShare": 21.79550963038795,
        "shareholdersEquityPerShare": 14.584182775212687,
        "interestDebtPerShare": 11.93023113519132,
        "marketCap": 152266521328.4544,
        "enterpriseValue": 177851521328.4544,
        "peRatio": 38.84350033889143,
        "priceToSalesRatio": 3.825119233513061,
        "pocfratio": 14.674876766427758,
        "pfcfRatio": 17.378055390145448,
        "pbRatio": 3.798306758343006,
        "ptbRatio": 3.798306758343006,
        "evToSales": 4.467845387204623,
        "enterpriseValueOverEBITDA": 15.308273483254812,
        "evToOperatingCashFlow": 17.14066319665135,
        "evToFreeCashFlow": 20.298050824977675,
        "earningsYield": 0.025744332804084755,
        "freeCashFlowYield": 0.05754383776259965,
        "debtToEquity": 1.3737028537218121,
        "debtToAssets": 0.577382387787412,
        "netDebtToEBITDA": 2.202186262695817,
        "currentRatio": 1.7794698907230877,
        "interestCoverage": 6.7229437229437226,
        "incomeQuality": 2.646938775510204,
        "dividendYield": 0.033651520736767936,
        "payoutRatio": 1.3071428571428572,
        "salesGeneralAndAdministrativeToRevenue": 0.24523325043334088,
        "researchAndDdevelopementToRevenue": 0.2543271283945035,
        "intangiblesToTotalAssets": 0.371861140526542,
        "capexToOperatingCashFlow": -6.428748451053284,
        "capexToRevenue": -24.6635687732342,
        "capexToDepreciation": -3.3711276332094178,
        "stockBasedCompensationToRevenue": 0.0075363629512397315,
        "grahamNumber": 21.632623717946423,
        "roic": 0.05959858263083162,
        "returnOnTangibleAssets": 0.06543148055416458,
        "grahamNetNet": -12.016998436924712,
        "workingCapital": 13410000000,
        "tangibleAssetValue": 4841000000,
        "netCurrentAssetValue": -24455000000,
        "investedCapital": null,
        "averageReceivables": 7044500000,
        "averagePayables": 3062500000,
        "averageInventory": 5153000000,
        "daysSalesOutstanding": 64.3497374833572,
        "daysPayablesOutstanding": 73.75674897415593,
        "daysOfInventoryOnHand": 127.85904542509539,
        "receivablesTurnover": 5.672128811627244,
        "payablesTurnover": 4.9486996793729965,
        "inventoryTurnover": 2.8547061241265927,
        "roe": 0.09778487327878667,
        "capexPerShare": -0.5871799790259749
    },
    {
        "symbol": "MRK",
        "date": "2015-12-31",
        "revenuePerShare": 14.202150696855016,
        "netIncomePerShare": 1.5971936147508732,
        "operatingCashFlowPerShare": 4.466173320310805,
        "freeCashFlowPerShare": 4.004849725595503,
        "cashPerShare": 3.0649433525746157,
        "bookValuePerShare": 16.063985126656913,
        "tangibleBookValuePerShare": 22.096788924110797,
        "shareholdersEquityPerShare": 16.063985126656913,
        "interestDebtPerShare": 10.608644846827952,
        "marketCap": 123099681331.1625,
        "enterpriseValue": 143407681331.1625,
        "peRatio": 27.71267026815905,
        "priceToSalesRatio": 3.116605431443681,
        "pocfratio": 9.910609558905282,
        "pfcfRatio": 11.05222493546081,
        "pbRatio": 2.755387262314498,
        "ptbRatio": 2.755387262314498,
        "evToSales": 3.6307580467659757,
        "enterpriseValueOverEBITDA": 9.997746885886956,
        "evToOperatingCashFlow": 11.545582588452017,
        "evToFreeCashFlow": 12.875532531079413,
        "earningsYield": 0.03608457757132726,
        "freeCashFlowYield": 0.09047951935827174,
        "debtToEquity": 1.2761214074670963,
        "debtToAssets": 0.560154845302076,
        "netDebtToEBITDA": 1.4157836029001674,
        "currentRatio": 1.5499661511222205,
        "interestCoverage": 8.037202380952381,
        "incomeQuality": 2.796262944619541,
        "dividendYield": 0.041567938638559565,
        "payoutRatio": 1.1519585772174696,
        "salesGeneralAndAdministrativeToRevenue": 0.26110182794065523,
        "researchAndDdevelopementToRevenue": 0.16973011291710974,
        "intangiblesToTotalAssets": 0.39620157399856554,
        "capexToOperatingCashFlow": -9.681215900233827,
        "capexToRevenue": -30.785658612626655,
        "capexToDepreciation": -4.968823070927514,
        "stockBasedCompensationToRevenue": 0.007570003544483265,
        "grahamNumber": 24.026841773615647,
        "roic": 0.06540641348575857,
        "returnOnTangibleAssets": 0.07228170664236665,
        "grahamNetNet": -13.078146365537766,
        "workingCapital": 10561000000,
        "tangibleAssetValue": 4442000000,
        "netCurrentAssetValue": -27248000000,
        "investedCapital": null,
        "averageReceivables": 6777500000,
        "averagePayables": 2925500000,
        "averageInventory": 5070000000,
        "daysSalesOutstanding": 59.918476884905566,
        "daysPayablesOutstanding": 61.908731753046744,
        "daysOfInventoryOnHand": 114.87210392393197,
        "receivablesTurnover": 6.091610117211598,
        "payablesTurnover": 5.895775759968417,
        "inventoryTurnover": 3.177446808510638,
        "roe": 0.09942698540603456,
        "capexPerShare": -0.4613235947153017
    }
]